{
  "schema_version": 3,
  "symbol": "000510.SZ",
  "name": "SICHUAN XINJINLU GROUP CO.,LTD",
  "exchange": "SZSE",
  "currency": "CNY",
  "market": "CN",
  "indexes": [
    "csi2000",
    "csi_all"
  ],
  "sources": [
    "yfinance"
  ],
  "fetched_at": "2026-06-17T08:33:22.777509+00:00",
  "market_data": {
    "as_of": "2026-07-07",
    "price": 19.68000030517578,
    "shares_outstanding": 648543589,
    "shares_source": "yfinance.fast_info",
    "shares_kind": "current_shares_outstanding",
    "shares_refreshed_at": "2026-07-07T23:29:45.505039+00:00",
    "market_cap": 12763338029.439796,
    "cash_and_short_term_investments": 223366387.61,
    "total_debt": 500480495.77,
    "enterprise_value": 13040452137.599796
  },
  "ttm": {
    "revenue": null,
    "net_income": null,
    "diluted_eps": null,
    "free_cash_flow": -270061272.47,
    "operating_cash_flow": null,
    "capital_expenditure": -226979738.01000002,
    "revenue_per_share": null,
    "free_cash_flow_per_share": -0.4164119066945245,
    "net_margin": null,
    "cash_conversion": null
  },
  "valuation_bases": {
    "revenue": {
      "value": 1659574903.91,
      "period": "2025-12-31",
      "per_share": 2.558925771618413
    },
    "earnings": {
      "value": -230350061.03,
      "period": "2025-12-31",
      "per_share": -0.35518053826602547
    },
    "free_cash_flow": {
      "value": -270061272.47,
      "period": "ttm",
      "per_share": -0.4164119066945245
    }
  },
  "annual": [
    {
      "fiscal_year": "2025-12-31",
      "source": "yfinance",
      "revenue": 1659574903.91,
      "net_income": -230350061.03,
      "diluted_eps": -0.3552,
      "diluted_shares": 648508055,
      "operating_cash_flow": 16864455.22,
      "capital_expenditure": -160674047.32,
      "free_cash_flow": -143809592.1,
      "revenue_per_share": 2.5590659840146475,
      "free_cash_flow_per_share": -0.22175451945620012,
      "net_margin": -0.13880064134935366,
      "cash_conversion": 0.6243088951527159,
      "year_end_price": 11.579999923706055,
      "price_to_earnings": -32.601351136559835,
      "price_to_fcf": -52.21990492957362
    },
    {
      "fiscal_year": "2024-12-31",
      "source": "yfinance",
      "revenue": 2037122003.84,
      "net_income": -62542274.5,
      "diluted_eps": -0.1005,
      "diluted_shares": 622311189,
      "operating_cash_flow": -105686460.74,
      "capital_expenditure": -60705341.46,
      "free_cash_flow": -166391802.2,
      "revenue_per_share": 3.273478028112395,
      "free_cash_flow_per_share": -0.267377166184939,
      "net_margin": -0.030701290537389046,
      "cash_conversion": 2.660469315039062,
      "year_end_price": 3.5999999046325684,
      "price_to_earnings": -35.82089457345839,
      "price_to_fcf": -13.464126185489325
    },
    {
      "fiscal_year": "2023-12-31",
      "source": "yfinance",
      "revenue": 2589304485.83,
      "net_income": -176643061.36,
      "diluted_eps": -0.29,
      "diluted_shares": 609114005,
      "operating_cash_flow": -121123896.5,
      "capital_expenditure": -33980128.97,
      "free_cash_flow": -155104025.47,
      "revenue_per_share": 4.250935727261763,
      "free_cash_flow_per_share": -0.254638744466235,
      "net_margin": -0.06822027394873074,
      "cash_conversion": 0.8780646365378413,
      "year_end_price": 5.670000076293945,
      "price_to_earnings": -19.551724401013605,
      "price_to_fcf": -22.266839589470976
    },
    {
      "fiscal_year": "2022-12-31",
      "source": "yfinance",
      "revenue": 3038820516.07,
      "net_income": 12999191.68,
      "diluted_eps": 0.0213,
      "diluted_shares": 610290689,
      "operating_cash_flow": -19411619,
      "capital_expenditure": -82622401.77,
      "free_cash_flow": -102034020.77,
      "revenue_per_share": 4.979300144738076,
      "free_cash_flow_per_share": -0.16718921426966094,
      "net_margin": 0.004277709595304232,
      "cash_conversion": -7.849258883303119,
      "year_end_price": 5.860000133514404,
      "price_to_earnings": 275.1173771603007,
      "price_to_fcf": -35.05010869937315
    }
  ],
  "historical_metrics": {
    "available_growth_windows": {
      "revenue": [
        1,
        3
      ],
      "earnings": [
        1,
        3
      ],
      "free_cash_flow": [
        1,
        3
      ]
    },
    "growth": {
      "revenue": {
        "1y": -0.185333573157778,
        "3y": -0.18260758566801016,
        "5y": null,
        "10y": null
      },
      "earnings": {
        "1y": null,
        "3y": null,
        "5y": null,
        "10y": null
      },
      "free_cash_flow": {
        "1y": null,
        "3y": null,
        "5y": null,
        "10y": null
      }
    },
    "averages": {
      "net_margin": {
        "1y": -0.13880064134935366,
        "3y": -0.07924073527849114,
        "5y": null,
        "10y": null
      },
      "cash_conversion": {
        "1y": 0.6243088951527159,
        "3y": 1.3876142822432065,
        "5y": null,
        "10y": null
      },
      "price_to_earnings": {
        "1y": -32.601351136559835,
        "3y": -29.324656703677274,
        "5y": null,
        "10y": null
      },
      "price_to_fcf": {
        "1y": -52.21990492957362,
        "3y": -29.316956901511308,
        "5y": null,
        "10y": null
      }
    }
  },
  "calculator_contract": {
    "forward_models": {
      "revenue_growth": {
        "base": "valuation_bases.revenue.per_share",
        "margin": "user_input.net_margin",
        "terminal_multiple": "user_input.terminal_pe"
      },
      "earnings_growth": {
        "base": "valuation_bases.earnings.per_share",
        "terminal_multiple": "user_input.terminal_pe"
      },
      "fcf_growth": {
        "base": "valuation_bases.free_cash_flow.per_share",
        "terminal_multiple": "user_input.terminal_price_to_fcf"
      }
    },
    "common_user_inputs": [
      "projection_years",
      "growth_rate",
      "discount_rate"
    ],
    "forward_output": "fair_value_per_share",
    "reverse_output": "implied_compound_growth_rate"
  },
  "data_quality": {
    "warnings": [
      "fewer than 5 annual financial periods are available"
    ]
  },
  "price_refreshed_at": "2026-07-07T23:29:45.505045+00:00"
}
