{
  "schema_version": 3,
  "symbol": "001299.SZ",
  "name": "Shaanxi Meineng Clean Energy Corp.,Ltd.",
  "exchange": "SZSE",
  "currency": "CNY",
  "market": "CN",
  "indexes": [
    "csi_all"
  ],
  "sources": [
    "yfinance"
  ],
  "fetched_at": "2026-06-17T08:22:14.099178+00:00",
  "market_data": {
    "as_of": "2026-07-07",
    "price": 10.180000305175781,
    "shares_outstanding": 314215187,
    "shares_source": "yfinance.fast_info",
    "shares_kind": "current_shares_outstanding",
    "shares_refreshed_at": "2026-07-07T23:30:20.746745+00:00",
    "market_cap": 3198710699.550865,
    "cash_and_short_term_investments": 493168303.07,
    "total_debt": 9758371.47,
    "enterprise_value": 2715300767.950865
  },
  "ttm": {
    "revenue": 818720979.75,
    "net_income": 115440252.39000002,
    "diluted_eps": null,
    "free_cash_flow": -22636684.730000004,
    "operating_cash_flow": null,
    "capital_expenditure": -117624363.35,
    "revenue_per_share": 2.5955695221713198,
    "free_cash_flow_per_share": -0.0717644843865245,
    "net_margin": 0.14100072582145165,
    "cash_conversion": -0.19609004884643602
  },
  "valuation_bases": {
    "revenue": {
      "value": 818720979.75,
      "period": "ttm",
      "per_share": 2.5955695221713198
    },
    "earnings": {
      "value": 115440252.39000002,
      "period": "ttm",
      "per_share": 0.3659771865461945
    },
    "free_cash_flow": {
      "value": -22636684.730000004,
      "period": "ttm",
      "per_share": -0.0717644843865245
    }
  },
  "annual": [
    {
      "fiscal_year": "2025-12-31",
      "source": "yfinance",
      "revenue": 725540857.14,
      "net_income": 102487410.11,
      "diluted_eps": 0.330769,
      "diluted_shares": 309845658,
      "operating_cash_flow": 89146680.99,
      "capital_expenditure": -99347449.12,
      "free_cash_flow": -10200768.13,
      "revenue_per_share": 2.3416202177020664,
      "free_cash_flow_per_share": -0.03292209481276643,
      "net_margin": 0.14125656618979912,
      "cash_conversion": -0.09953191439857335,
      "year_end_price": 11.315383911132812,
      "price_to_earnings": 34.209324063418315,
      "price_to_fcf": -343.7018201753361
    },
    {
      "fiscal_year": "2024-12-31",
      "source": "yfinance",
      "revenue": 665208472.27,
      "net_income": 87298199.69,
      "diluted_eps": 0.276923,
      "diluted_shares": 315243499,
      "operating_cash_flow": 99760451.85,
      "capital_expenditure": -73864897.6,
      "free_cash_flow": 25895554.25,
      "revenue_per_share": 2.110141761464207,
      "free_cash_flow_per_share": 0.0821446099035971,
      "net_margin": 0.13123434731986805,
      "cash_conversion": 0.2966333136531604,
      "year_end_price": 7.360946178436279,
      "price_to_earnings": 26.581201916909322,
      "price_to_fcf": 89.60960660808915
    },
    {
      "fiscal_year": "2023-12-31",
      "source": "yfinance",
      "revenue": 575789775.06,
      "net_income": 81810612.3,
      "diluted_eps": 0.260355,
      "diluted_shares": 314227125,
      "operating_cash_flow": 91707217.51,
      "capital_expenditure": -34410959.57,
      "free_cash_flow": 57296257.94,
      "revenue_per_share": 1.832399972026603,
      "free_cash_flow_per_share": 0.1823402672191333,
      "net_margin": 0.14208417002798454,
      "cash_conversion": 0.7003523910797084,
      "year_end_price": 9.189349174499512,
      "price_to_earnings": 35.295458794720716,
      "price_to_fcf": 50.396707839941435
    },
    {
      "fiscal_year": "2022-12-31",
      "source": "yfinance",
      "revenue": 549897584.35,
      "net_income": 94222814.39,
      "diluted_eps": 0.372781,
      "diluted_shares": 252756439,
      "operating_cash_flow": 138179110.44,
      "capital_expenditure": -27471457.08,
      "free_cash_flow": 110707653.36,
      "revenue_per_share": 2.1756026731726505,
      "free_cash_flow_per_share": 0.4380013177824522,
      "net_margin": 0.17134611438850922,
      "cash_conversion": 1.1749559178074134,
      "year_end_price": 11.952662467956543,
      "price_to_earnings": 32.06349698068449,
      "price_to_fcf": 27.28910161382945
    }
  ],
  "historical_metrics": {
    "available_growth_windows": {
      "revenue": [
        1,
        3
      ],
      "earnings": [
        1,
        3
      ],
      "free_cash_flow": [
        1,
        3
      ]
    },
    "growth": {
      "revenue": {
        "1y": 0.09069695799892319,
        "3y": 0.09679809455423527,
        "5y": null,
        "10y": null
      },
      "earnings": {
        "1y": 0.17399225269178054,
        "3y": 0.028422292654195047,
        "5y": null,
        "10y": null
      },
      "free_cash_flow": {
        "1y": null,
        "3y": null,
        "5y": null,
        "10y": null
      }
    },
    "averages": {
      "net_margin": {
        "1y": 0.14125656618979912,
        "3y": 0.13819169451255056,
        "5y": null,
        "10y": null
      },
      "cash_conversion": {
        "1y": -0.09953191439857335,
        "3y": 0.2991512634447651,
        "5y": null,
        "10y": null
      },
      "price_to_earnings": {
        "1y": 34.209324063418315,
        "3y": 32.028661591682784,
        "5y": null,
        "10y": null
      },
      "price_to_fcf": {
        "1y": -343.7018201753361,
        "3y": -67.89850190910182,
        "5y": null,
        "10y": null
      }
    }
  },
  "calculator_contract": {
    "forward_models": {
      "revenue_growth": {
        "base": "valuation_bases.revenue.per_share",
        "margin": "user_input.net_margin",
        "terminal_multiple": "user_input.terminal_pe"
      },
      "earnings_growth": {
        "base": "valuation_bases.earnings.per_share",
        "terminal_multiple": "user_input.terminal_pe"
      },
      "fcf_growth": {
        "base": "valuation_bases.free_cash_flow.per_share",
        "terminal_multiple": "user_input.terminal_price_to_fcf"
      }
    },
    "common_user_inputs": [
      "projection_years",
      "growth_rate",
      "discount_rate"
    ],
    "forward_output": "fair_value_per_share",
    "reverse_output": "implied_compound_growth_rate"
  },
  "data_quality": {
    "warnings": [
      "fewer than 5 annual financial periods are available"
    ]
  },
  "price_refreshed_at": "2026-07-07T23:30:20.746752+00:00"
}
