{
  "schema_version": 3,
  "symbol": "601818.SS",
  "name": "China Everbright Bank Co Ltd",
  "exchange": "SSE",
  "currency": "CNY",
  "market": "CN",
  "indexes": [
    "csi300",
    "csi800",
    "csi_all"
  ],
  "sources": [
    "yfinance"
  ],
  "fetched_at": "2026-06-16T12:14:22.549329+00:00",
  "market_data": {
    "as_of": "2026-07-03",
    "price": 2.9800000190734863,
    "shares_outstanding": 59085551061,
    "shares_source": "yfinance.fast_info",
    "shares_kind": "current_shares_outstanding",
    "shares_refreshed_at": "2026-07-03T23:40:57.154627+00:00",
    "market_cap": 176074943288.74744,
    "cash_and_short_term_investments": 585351000000,
    "total_debt": 1535952000000,
    "enterprise_value": 1126675943288.7476
  },
  "ttm": {
    "revenue": 129770000000,
    "net_income": 37889000000,
    "diluted_eps": null,
    "free_cash_flow": 114658000000,
    "operating_cash_flow": 120680000000,
    "capital_expenditure": -6022000000,
    "revenue_per_share": 2.19630684100797,
    "free_cash_flow_per_share": 1.9405421112452168,
    "net_margin": 0.291970409185482,
    "cash_conversion": 3.0261553485180395
  },
  "valuation_bases": {
    "revenue": {
      "value": 129770000000,
      "period": "ttm",
      "per_share": 2.19630684100797
    },
    "earnings": {
      "value": 37889000000,
      "period": "ttm",
      "per_share": 0.6412566070659703
    },
    "free_cash_flow": {
      "value": 114658000000,
      "period": "ttm",
      "per_share": 1.9405421112452168
    }
  },
  "annual": [
    {
      "fiscal_year": "2025-12-31",
      "source": "yfinance",
      "revenue": 126311000000,
      "net_income": 38826000000,
      "diluted_eps": 0.58,
      "diluted_shares": 66941379310,
      "operating_cash_flow": 162907000000,
      "capital_expenditure": -7512000000,
      "free_cash_flow": 155395000000,
      "revenue_per_share": 1.8868897130885844,
      "free_cash_flow_per_share": 2.3213593983532754,
      "net_margin": 0.30738415498254307,
      "cash_conversion": 4.002343790243651,
      "year_end_price": 3.490000009536743,
      "price_to_earnings": 6.017241395753006,
      "price_to_fcf": 1.5034294181299446
    },
    {
      "fiscal_year": "2024-12-31",
      "source": "yfinance",
      "revenue": 135402000000,
      "net_income": 41696000000,
      "diluted_eps": 0.62,
      "diluted_shares": 67251612903,
      "operating_cash_flow": -204802000000,
      "capital_expenditure": -9400000000,
      "free_cash_flow": -214202000000,
      "revenue_per_share": 2.0133643515033066,
      "free_cash_flow_per_share": -3.185083461253979,
      "net_margin": 0.30794227559415666,
      "cash_conversion": -5.137231389102072,
      "year_end_price": 3.869999885559082,
      "price_to_earnings": 6.241935299288842,
      "price_to_fcf": -1.2150387682574098
    },
    {
      "fiscal_year": "2023-12-31",
      "source": "yfinance",
      "revenue": 145649000000,
      "net_income": 40792000000,
      "diluted_eps": 0.61,
      "diluted_shares": 66872131148,
      "operating_cash_flow": -3614000000,
      "capital_expenditure": -5154000000,
      "free_cash_flow": -8768000000,
      "revenue_per_share": 2.178022406339237,
      "free_cash_flow_per_share": -0.13111590507852736,
      "net_margin": 0.28007058064250356,
      "cash_conversion": -0.2149441066875858,
      "year_end_price": 2.9000000953674316,
      "price_to_earnings": 4.75409851699579,
      "price_to_fcf": -22.117836075116717
    },
    {
      "fiscal_year": "2022-12-31",
      "source": "yfinance",
      "revenue": 151695000000,
      "net_income": 44807000000,
      "diluted_eps": 0.67,
      "diluted_shares": 66876119403,
      "operating_cash_flow": -56398000000,
      "capital_expenditure": -4667000000,
      "free_cash_flow": -61065000000,
      "revenue_per_share": 2.268298480147685,
      "free_cash_flow_per_share": -0.9131062110828859,
      "net_margin": 0.2953755891756485,
      "cash_conversion": -1.3628450911687906,
      "year_end_price": 3.069999933242798,
      "price_to_earnings": 4.58208945260119,
      "price_to_fcf": -3.362149874768646
    }
  ],
  "historical_metrics": {
    "available_growth_windows": {
      "revenue": [
        1,
        3
      ],
      "earnings": [
        1,
        3
      ],
      "free_cash_flow": [
        1,
        3
      ]
    },
    "growth": {
      "revenue": {
        "1y": -0.06714081032776475,
        "3y": -0.05921589961295726,
        "5y": null,
        "10y": null
      },
      "earnings": {
        "1y": -0.0688315425940138,
        "3y": -0.046635606688753106,
        "5y": null,
        "10y": null
      },
      "free_cash_flow": {
        "1y": null,
        "3y": null,
        "5y": null,
        "10y": null
      }
    },
    "averages": {
      "net_margin": {
        "1y": 0.30738415498254307,
        "3y": 0.2984656704064011,
        "5y": null,
        "10y": null
      },
      "cash_conversion": {
        "1y": 4.002343790243651,
        "3y": -0.4499439018486691,
        "5y": null,
        "10y": null
      },
      "price_to_earnings": {
        "1y": 6.017241395753006,
        "3y": 5.671091737345879,
        "5y": null,
        "10y": null
      },
      "price_to_fcf": {
        "1y": 1.5034294181299446,
        "3y": -7.276481808414727,
        "5y": null,
        "10y": null
      }
    }
  },
  "calculator_contract": {
    "forward_models": {
      "revenue_growth": {
        "base": "valuation_bases.revenue.per_share",
        "margin": "user_input.net_margin",
        "terminal_multiple": "user_input.terminal_pe"
      },
      "earnings_growth": {
        "base": "valuation_bases.earnings.per_share",
        "terminal_multiple": "user_input.terminal_pe"
      },
      "fcf_growth": {
        "base": "valuation_bases.free_cash_flow.per_share",
        "terminal_multiple": "user_input.terminal_price_to_fcf"
      }
    },
    "common_user_inputs": [
      "projection_years",
      "growth_rate",
      "discount_rate"
    ],
    "forward_output": "fair_value_per_share",
    "reverse_output": "implied_compound_growth_rate"
  },
  "data_quality": {
    "warnings": [
      "fewer than 5 annual financial periods are available"
    ]
  },
  "price_refreshed_at": "2026-07-03T23:40:57.154633+00:00"
}
