{
  "schema_version": 3,
  "symbol": "601928.SS",
  "name": "Jiangsu Phoenix Publishing & Media Co Ltd",
  "exchange": "SSE",
  "currency": "CNY",
  "market": "CN",
  "indexes": [
    "csi500",
    "csi800",
    "csi_all"
  ],
  "sources": [
    "yfinance"
  ],
  "fetched_at": "2026-06-17T07:25:34.201156+00:00",
  "market_data": {
    "as_of": "2026-07-02",
    "price": 9.029999732971191,
    "shares_outstanding": 2544900000,
    "shares_source": "yfinance.fast_info",
    "shares_kind": "current_shares_outstanding",
    "shares_refreshed_at": "2026-07-02T23:45:35.406310+00:00",
    "market_cap": 22980446320.438385,
    "cash_and_short_term_investments": 7479011882.14,
    "total_debt": 208443572.04,
    "enterprise_value": 15709878010.338387
  },
  "ttm": {
    "revenue": 13184906019.640001,
    "net_income": 2102663739.7099998,
    "diluted_eps": null,
    "free_cash_flow": 733757220.1600001,
    "operating_cash_flow": null,
    "capital_expenditure": -190506285.14,
    "revenue_per_share": 5.180913206664309,
    "free_cash_flow_per_share": 0.2883245786317734,
    "net_margin": 0.15947506463663141,
    "cash_conversion": 0.3489655555962553
  },
  "valuation_bases": {
    "revenue": {
      "value": 13184906019.640001,
      "period": "ttm",
      "per_share": 5.180913206664309
    },
    "earnings": {
      "value": 2102663739.7099998,
      "period": "ttm",
      "per_share": 0.826226468509568
    },
    "free_cash_flow": {
      "value": 733757220.1600001,
      "period": "ttm",
      "per_share": 0.2883245786317734
    }
  },
  "annual": [
    {
      "fiscal_year": "2025-12-31",
      "source": "yfinance",
      "revenue": 12346723810.27,
      "net_income": 1795138915.12,
      "diluted_eps": 0.71,
      "diluted_shares": 2528364669,
      "operating_cash_flow": 1536468206.1,
      "capital_expenditure": -197759154.65,
      "free_cash_flow": 1338709051.45,
      "revenue_per_share": 4.883284425562427,
      "free_cash_flow_per_share": 0.5294762531148153,
      "net_margin": 0.14539394763384955,
      "cash_conversion": 0.7457412015161574,
      "year_end_price": 10.039999961853027,
      "price_to_earnings": 14.140845016694405,
      "price_to_fcf": 18.962134567489063
    },
    {
      "fiscal_year": "2024-12-31",
      "source": "yfinance",
      "revenue": 13605834830.28,
      "net_income": 1597505168.2,
      "diluted_eps": 0.63,
      "diluted_shares": 2535722489,
      "operating_cash_flow": 1839329518.33,
      "capital_expenditure": -245682917.52,
      "free_cash_flow": 1593646600.81,
      "revenue_per_share": 5.365663983066879,
      "free_cash_flow_per_share": 0.6284783164258949,
      "net_margin": 0.11741324131355226,
      "cash_conversion": 0.997584629166272,
      "year_end_price": 11.539999961853027,
      "price_to_earnings": 18.317460256909566,
      "price_to_fcf": 18.361810837770932
    },
    {
      "fiscal_year": "2023-12-31",
      "source": "yfinance",
      "revenue": 13645039404.43,
      "net_income": 2951938135.73,
      "diluted_eps": 1.16,
      "diluted_shares": 2544774255,
      "operating_cash_flow": 2603125168.88,
      "capital_expenditure": -467189902.26,
      "free_cash_flow": 2135935266.62,
      "revenue_per_share": 5.361984222223279,
      "free_cash_flow_per_share": 0.8393417460992035,
      "net_margin": 0.2163378241891792,
      "cash_conversion": 0.7235704707923337,
      "year_end_price": 8.8100004196167,
      "price_to_earnings": 7.594827947945431,
      "price_to_fcf": 10.4963210284258
    },
    {
      "fiscal_year": "2022-12-31",
      "source": "yfinance",
      "revenue": 13595853156.81,
      "net_income": 2081792933.19,
      "diluted_eps": 0.818,
      "diluted_shares": 2544979136,
      "operating_cash_flow": 2506841773.17,
      "capital_expenditure": -608052251.57,
      "free_cash_flow": 1898789521.6,
      "revenue_per_share": 5.342225782714629,
      "free_cash_flow_per_share": 0.7460923725230885,
      "net_margin": 0.15311969827706287,
      "cash_conversion": 0.9120933649680624,
      "year_end_price": 7.920000076293945,
      "price_to_earnings": 9.682151682510936,
      "price_to_fcf": 10.615307658903662
    }
  ],
  "historical_metrics": {
    "available_growth_windows": {
      "revenue": [
        1,
        3
      ],
      "earnings": [
        1,
        3
      ],
      "free_cash_flow": [
        1,
        3
      ]
    },
    "growth": {
      "revenue": {
        "1y": -0.09254198920655932,
        "3y": -0.03161417733358041,
        "5y": null,
        "10y": null
      },
      "earnings": {
        "1y": 0.12371399533103555,
        "3y": -0.04818288320031694,
        "5y": null,
        "10y": null
      },
      "free_cash_flow": {
        "1y": -0.15997119388352676,
        "3y": -0.10997311723876768,
        "5y": null,
        "10y": null
      }
    },
    "averages": {
      "net_margin": {
        "1y": 0.14539394763384955,
        "3y": 0.15971500437886033,
        "5y": null,
        "10y": null
      },
      "cash_conversion": {
        "1y": 0.7457412015161574,
        "3y": 0.8222987671582543,
        "5y": null,
        "10y": null
      },
      "price_to_earnings": {
        "1y": 14.140845016694405,
        "3y": 13.351044407183133,
        "5y": null,
        "10y": null
      },
      "price_to_fcf": {
        "1y": 18.962134567489063,
        "3y": 15.940088811228597,
        "5y": null,
        "10y": null
      }
    }
  },
  "calculator_contract": {
    "forward_models": {
      "revenue_growth": {
        "base": "valuation_bases.revenue.per_share",
        "margin": "user_input.net_margin",
        "terminal_multiple": "user_input.terminal_pe"
      },
      "earnings_growth": {
        "base": "valuation_bases.earnings.per_share",
        "terminal_multiple": "user_input.terminal_pe"
      },
      "fcf_growth": {
        "base": "valuation_bases.free_cash_flow.per_share",
        "terminal_multiple": "user_input.terminal_price_to_fcf"
      }
    },
    "common_user_inputs": [
      "projection_years",
      "growth_rate",
      "discount_rate"
    ],
    "forward_output": "fair_value_per_share",
    "reverse_output": "implied_compound_growth_rate"
  },
  "data_quality": {
    "warnings": [
      "fewer than 5 annual financial periods are available"
    ]
  },
  "price_refreshed_at": "2026-07-02T23:45:35.406316+00:00"
}
