{
  "schema_version": 3,
  "symbol": "603863.SS",
  "name": "Guangdong Songyang Recycle Resources Co.,LTD",
  "exchange": "SSE",
  "currency": "CNY",
  "market": "CN",
  "indexes": [
    "csi_all"
  ],
  "sources": [
    "yfinance"
  ],
  "fetched_at": "2026-06-17T08:32:16.956652+00:00",
  "market_data": {
    "as_of": "2026-06-25",
    "price": 14.229999542236328,
    "shares_outstanding": 204650000,
    "shares_source": "yfinance.fast_info",
    "shares_kind": "current_shares_outstanding",
    "shares_refreshed_at": "2026-06-25T10:29:20.079717+00:00",
    "market_cap": 2912169406.3186646,
    "cash_and_short_term_investments": 11433479.44,
    "total_debt": 345826721.48,
    "enterprise_value": 3246562648.3586645
  },
  "ttm": {
    "revenue": 472830951.43,
    "net_income": -167698205.14,
    "diluted_eps": null,
    "free_cash_flow": -27160380.86,
    "operating_cash_flow": null,
    "capital_expenditure": -7251564.0200000005,
    "revenue_per_share": 2.3104370946982655,
    "free_cash_flow_per_share": -0.13271625145370144,
    "net_margin": -0.3546684171855166,
    "cash_conversion": 0.161959878087697
  },
  "valuation_bases": {
    "revenue": {
      "value": 472830951.43,
      "period": "ttm",
      "per_share": 2.3104370946982655
    },
    "earnings": {
      "value": -167698205.14,
      "period": "ttm",
      "per_share": -0.8194390673833374
    },
    "free_cash_flow": {
      "value": -27160380.86,
      "period": "ttm",
      "per_share": -0.13271625145370144
    }
  },
  "annual": [
    {
      "fiscal_year": "2025-12-31",
      "source": "yfinance",
      "revenue": 443167199.74,
      "net_income": -203651183.52,
      "diluted_eps": -1,
      "diluted_shares": 203651184,
      "operating_cash_flow": -24300902.07,
      "capital_expenditure": -7587492.29,
      "free_cash_flow": -31888394.36,
      "revenue_per_share": 2.1761091246098525,
      "free_cash_flow_per_share": -0.15658339781614036,
      "net_margin": -0.459535777105073,
      "cash_conversion": 0.15658339818520292,
      "year_end_price": 19.950000762939453,
      "price_to_earnings": -19.950000762939453,
      "price_to_fcf": -127.40814825314156
    },
    {
      "fiscal_year": "2024-12-31",
      "source": "yfinance",
      "revenue": 708887043.54,
      "net_income": -235619847.04,
      "diluted_eps": -1.15,
      "diluted_shares": 204886824,
      "operating_cash_flow": 8577467.35,
      "capital_expenditure": -25904597.22,
      "free_cash_flow": -17327129.87,
      "revenue_per_share": 3.4598957107168586,
      "free_cash_flow_per_share": -0.08456927357124731,
      "net_margin": -0.3323799598076655,
      "cash_conversion": 0.07353849893238604,
      "year_end_price": 20.110000610351562,
      "price_to_earnings": -17.48695705247962,
      "price_to_fcf": -237.79322868854294
    },
    {
      "fiscal_year": "2023-12-31",
      "source": "yfinance",
      "revenue": 619892358.54,
      "net_income": -236931005.82,
      "diluted_eps": -1.16,
      "diluted_shares": 204250867,
      "operating_cash_flow": -28568104.85,
      "capital_expenditure": -36637354,
      "free_cash_flow": -65205458.85,
      "revenue_per_share": 3.0349558248876365,
      "free_cash_flow_per_share": -0.3192420174647288,
      "net_margin": -0.3822131416138621,
      "cash_conversion": 0.27520863562930026,
      "year_end_price": 33.83000183105469,
      "price_to_earnings": -29.1637946819437,
      "price_to_fcf": -105.96976582129378
    },
    {
      "fiscal_year": "2022-12-31",
      "source": "yfinance",
      "revenue": 928088633.34,
      "net_income": -277224556.74,
      "diluted_eps": -1.35,
      "diluted_shares": 205351524,
      "operating_cash_flow": -122644903.31,
      "capital_expenditure": -66154034.56,
      "free_cash_flow": -188798937.87,
      "revenue_per_share": 4.519511787699224,
      "free_cash_flow_per_share": -0.9193938968283479,
      "net_margin": -0.29870482923848113,
      "cash_conversion": 0.6810325177905089,
      "year_end_price": 12.850000381469727,
      "price_to_earnings": -9.518518801088685,
      "price_to_fcf": -13.976599611764486
    }
  ],
  "historical_metrics": {
    "available_growth_windows": {
      "revenue": [
        1,
        3
      ],
      "earnings": [
        1,
        3
      ],
      "free_cash_flow": [
        1,
        3
      ]
    },
    "growth": {
      "revenue": {
        "1y": -0.3748408808165872,
        "3y": -0.2183853002172642,
        "5y": null,
        "10y": null
      },
      "earnings": {
        "1y": null,
        "3y": null,
        "5y": null,
        "10y": null
      },
      "free_cash_flow": {
        "1y": null,
        "3y": null,
        "5y": null,
        "10y": null
      }
    },
    "averages": {
      "net_margin": {
        "1y": -0.459535777105073,
        "3y": -0.3913762928422002,
        "5y": null,
        "10y": null
      },
      "cash_conversion": {
        "1y": 0.15658339818520292,
        "3y": 0.16844351091562973,
        "5y": null,
        "10y": null
      },
      "price_to_earnings": {
        "1y": -19.950000762939453,
        "3y": -22.20025083245426,
        "5y": null,
        "10y": null
      },
      "price_to_fcf": {
        "1y": -127.40814825314156,
        "3y": -157.0570475876594,
        "5y": null,
        "10y": null
      }
    }
  },
  "calculator_contract": {
    "forward_models": {
      "revenue_growth": {
        "base": "valuation_bases.revenue.per_share",
        "margin": "user_input.net_margin",
        "terminal_multiple": "user_input.terminal_pe"
      },
      "earnings_growth": {
        "base": "valuation_bases.earnings.per_share",
        "terminal_multiple": "user_input.terminal_pe"
      },
      "fcf_growth": {
        "base": "valuation_bases.free_cash_flow.per_share",
        "terminal_multiple": "user_input.terminal_price_to_fcf"
      }
    },
    "common_user_inputs": [
      "projection_years",
      "growth_rate",
      "discount_rate"
    ],
    "forward_output": "fair_value_per_share",
    "reverse_output": "implied_compound_growth_rate"
  },
  "data_quality": {
    "warnings": [
      "fewer than 5 annual financial periods are available"
    ]
  },
  "price_refreshed_at": "2026-06-25T10:29:20.079723+00:00"
}
