{
  "schema_version": 3,
  "symbol": "688302.SS",
  "name": "Hinova Pharmaceuticals Inc.",
  "exchange": "SSE",
  "currency": "CNY",
  "market": "CN",
  "indexes": [
    "csi2000",
    "csi_all"
  ],
  "sources": [
    "yfinance"
  ],
  "fetched_at": "2026-06-17T08:23:31.972299+00:00",
  "market_data": {
    "as_of": "2026-06-29",
    "price": 35.04999923706055,
    "shares_outstanding": 99015598,
    "shares_source": "yfinance.fast_info",
    "shares_kind": "current_shares_outstanding",
    "shares_refreshed_at": "2026-06-29T23:41:46.570612+00:00",
    "market_cap": 3470496634.357094,
    "cash_and_short_term_investments": 827741617.14,
    "total_debt": 105036612.26,
    "enterprise_value": 2747791629.477094
  },
  "ttm": {
    "revenue": 36310688.13,
    "net_income": -129840635.64,
    "diluted_eps": null,
    "free_cash_flow": -163034606.70999998,
    "operating_cash_flow": null,
    "capital_expenditure": -75309262.73,
    "revenue_per_share": 0.36671684929883475,
    "free_cash_flow_per_share": -1.6465547853379623,
    "net_margin": -3.5758241533496378,
    "cash_conversion": 1.2556516371502875
  },
  "valuation_bases": {
    "revenue": {
      "value": 36310688.13,
      "period": "ttm",
      "per_share": 0.36671684929883475
    },
    "earnings": {
      "value": -129840635.64,
      "period": "ttm",
      "per_share": -1.3113149671630524
    },
    "free_cash_flow": {
      "value": -163034606.70999998,
      "period": "ttm",
      "per_share": -1.6465547853379623
    }
  },
  "annual": [
    {
      "fiscal_year": "2025-12-31",
      "source": "yfinance",
      "revenue": 20469871.8,
      "net_income": -137252611.25,
      "diluted_eps": -1.39,
      "diluted_shares": 98742886,
      "operating_cash_flow": -108878288.48,
      "capital_expenditure": -82886135.81,
      "free_cash_flow": -191764424.29,
      "revenue_per_share": 0.20730477535363914,
      "free_cash_flow_per_share": -1.942058127509054,
      "net_margin": -6.7051036074393,
      "cash_conversion": 1.3971641234621683,
      "year_end_price": 49.16999816894531,
      "price_to_earnings": -35.37409940211893,
      "price_to_fcf": -25.318499725861617
    },
    {
      "fiscal_year": "2024-12-31",
      "source": "yfinance",
      "revenue": 366836.28,
      "net_income": -199495736.1,
      "diluted_eps": -2.01,
      "diluted_shares": 99251610,
      "operating_cash_flow": -187083058.81,
      "capital_expenditure": -89549635.6,
      "free_cash_flow": -276632694.41,
      "revenue_per_share": 0.003696023470047489,
      "free_cash_flow_per_share": -2.7871859651445456,
      "net_margin": -543.8277154593324,
      "cash_conversion": 1.3866596841515153,
      "year_end_price": 30.709999084472656,
      "price_to_earnings": -15.27860650968789,
      "price_to_fcf": -11.01828133053189
    },
    {
      "fiscal_year": "2023-12-31",
      "source": "yfinance",
      "revenue": 0,
      "net_income": -294158414.14,
      "diluted_eps": -2.97,
      "diluted_shares": 99043237,
      "operating_cash_flow": -255507080.79,
      "capital_expenditure": -99176015.14,
      "free_cash_flow": -354683095.93,
      "revenue_per_share": 0.0,
      "free_cash_flow_per_share": -3.581093537259894,
      "net_margin": null,
      "cash_conversion": 1.205755398726056,
      "year_end_price": 52.06999969482422,
      "price_to_earnings": -17.531986429233744,
      "price_to_fcf": -14.540251225793462
    },
    {
      "fiscal_year": "2022-12-31",
      "source": "yfinance",
      "revenue": 1650822.41,
      "net_income": -301514838.08,
      "diluted_eps": -3.32,
      "diluted_shares": 90817722,
      "operating_cash_flow": -314923813.62,
      "capital_expenditure": -69207114.92,
      "free_cash_flow": -384130928.54,
      "revenue_per_share": 0.018177315766629776,
      "free_cash_flow_per_share": -4.229691299017608,
      "net_margin": -182.64522958590075,
      "cash_conversion": 1.2740033989242008,
      "year_end_price": 40.31999969482422,
      "price_to_earnings": -12.144578221332596,
      "price_to_fcf": -9.532610501430442
    }
  ],
  "historical_metrics": {
    "available_growth_windows": {
      "revenue": [
        1,
        3
      ],
      "earnings": [
        1,
        3
      ],
      "free_cash_flow": [
        1,
        3
      ]
    },
    "growth": {
      "revenue": {
        "1y": 54.801110511752,
        "3y": 1.314576764228387,
        "5y": null,
        "10y": null
      },
      "earnings": {
        "1y": null,
        "3y": null,
        "5y": null,
        "10y": null
      },
      "free_cash_flow": {
        "1y": null,
        "3y": null,
        "5y": null,
        "10y": null
      }
    },
    "averages": {
      "net_margin": {
        "1y": -6.7051036074393,
        "3y": -244.39268288422417,
        "5y": null,
        "10y": null
      },
      "cash_conversion": {
        "1y": 1.3971641234621683,
        "3y": 1.3298597354465798,
        "5y": null,
        "10y": null
      },
      "price_to_earnings": {
        "1y": -35.37409940211893,
        "3y": -22.728230780346852,
        "5y": null,
        "10y": null
      },
      "price_to_fcf": {
        "1y": -25.318499725861617,
        "3y": -16.95901076072899,
        "5y": null,
        "10y": null
      }
    }
  },
  "calculator_contract": {
    "forward_models": {
      "revenue_growth": {
        "base": "valuation_bases.revenue.per_share",
        "margin": "user_input.net_margin",
        "terminal_multiple": "user_input.terminal_pe"
      },
      "earnings_growth": {
        "base": "valuation_bases.earnings.per_share",
        "terminal_multiple": "user_input.terminal_pe"
      },
      "fcf_growth": {
        "base": "valuation_bases.free_cash_flow.per_share",
        "terminal_multiple": "user_input.terminal_price_to_fcf"
      }
    },
    "common_user_inputs": [
      "projection_years",
      "growth_rate",
      "discount_rate"
    ],
    "forward_output": "fair_value_per_share",
    "reverse_output": "implied_compound_growth_rate"
  },
  "data_quality": {
    "warnings": [
      "fewer than 5 annual financial periods are available"
    ]
  },
  "price_refreshed_at": "2026-06-29T23:41:46.570618+00:00"
}
