{
  "schema_version": 3,
  "symbol": "ADI",
  "name": "Analog Devices",
  "exchange": "US",
  "currency": "USD",
  "market": "US",
  "indexes": [
    "qqq",
    "sp500"
  ],
  "sources": [
    "sec-edgar",
    "yfinance"
  ],
  "fetched_at": "2026-06-16T04:58:27.589729+00:00",
  "market_data": {
    "as_of": "2026-06-15",
    "price": null,
    "shares_outstanding": 487087040,
    "market_cap": null,
    "cash_and_short_term_investments": 3439308000,
    "total_debt": 8684849000,
    "enterprise_value": null
  },
  "ttm": {
    "revenue": 12740193000,
    "net_income": 3313432000,
    "diluted_eps": 6.7299999999999995,
    "free_cash_flow": 4565150000,
    "operating_cash_flow": 5106471000,
    "capital_expenditure": -541321000,
    "revenue_per_share": 26.155885814576383,
    "free_cash_flow_per_share": 9.372349549682127,
    "net_margin": 0.26007706476660125,
    "cash_conversion": 1.3777708430412938
  },
  "valuation_bases": {
    "revenue": {
      "value": 12740193000,
      "period": "ttm",
      "per_share": 26.155885814576383
    },
    "earnings": {
      "value": 3313432000,
      "period": "ttm",
      "per_share": 6.7299999999999995
    },
    "free_cash_flow": {
      "value": 4565150000,
      "period": "ttm",
      "per_share": 9.372349549682127
    }
  },
  "annual": [
    {
      "fiscal_year": "2025-11-01",
      "source": "sec-edgar",
      "revenue": 11019707000,
      "net_income": 2267342000,
      "diluted_eps": 4.56,
      "diluted_shares": 496709000,
      "operating_cash_flow": 4812202000,
      "capital_expenditure": -533552000,
      "free_cash_flow": 4278650000,
      "revenue_per_share": 22.185438556579406,
      "free_cash_flow_per_share": 8.613997330428884,
      "net_margin": 0.20575338346110292,
      "cash_conversion": 1.887077467801505,
      "year_end_price": 234.1300048828125,
      "price_to_earnings": 51.34429931640626,
      "price_to_fcf": 27.180180803603218
    },
    {
      "fiscal_year": "2024-11-02",
      "source": "sec-edgar",
      "revenue": 9427157000,
      "net_income": 1635273000,
      "diluted_eps": 3.28,
      "diluted_shares": 498697000,
      "operating_cash_flow": 3852529000,
      "capital_expenditure": -730463000,
      "free_cash_flow": 3122066000,
      "revenue_per_share": 18.903576720934755,
      "free_cash_flow_per_share": 6.260446724163169,
      "net_margin": 0.17346406769294284,
      "cash_conversion": 1.9092017051587105,
      "year_end_price": 225.47999572753906,
      "price_to_earnings": 68.74390113644483,
      "price_to_fcf": 36.01659844133229
    },
    {
      "fiscal_year": "2023-10-28",
      "source": "sec-edgar",
      "revenue": 12305539000,
      "net_income": 3314579000,
      "diluted_eps": 6.55,
      "diluted_shares": 505959000,
      "operating_cash_flow": 4817634000,
      "capital_expenditure": -1261463000,
      "free_cash_flow": 3556171000,
      "revenue_per_share": 24.321217727128086,
      "free_cash_flow_per_share": 7.0285754379307415,
      "net_margin": 0.2693566693827877,
      "cash_conversion": 1.0728876879989888,
      "year_end_price": 160.57000732421875,
      "price_to_earnings": 24.51450493499523,
      "price_to_fcf": 22.845313213496876
    },
    {
      "fiscal_year": "2022-10-29",
      "source": "sec-edgar",
      "revenue": 12013953000,
      "net_income": 2748561000,
      "diluted_eps": 5.25,
      "diluted_shares": 523178000,
      "operating_cash_flow": 4475402000,
      "capital_expenditure": -699308000,
      "free_cash_flow": 3776094000,
      "revenue_per_share": 22.963413981474755,
      "free_cash_flow_per_share": 7.217608538585338,
      "net_margin": 0.22878073520014602,
      "cash_conversion": 1.3738439859984917,
      "year_end_price": 144.8800048828125,
      "price_to_earnings": 27.59619140625,
      "price_to_fcf": 20.07313144073746
    },
    {
      "fiscal_year": "2021-10-30",
      "source": "sec-edgar",
      "revenue": 7318286000,
      "net_income": 1390422000,
      "operating_cash_flow": 2735069000,
      "capital_expenditure": -343676000,
      "diluted_eps": 3.46,
      "diluted_shares": 401288000,
      "free_cash_flow": 2391393000,
      "revenue_per_share": 18.23699188612667,
      "free_cash_flow_per_share": 5.9592935746895,
      "net_margin": 0.18999284805212588,
      "cash_conversion": 1.7199044606601448,
      "year_end_price": 173.49000549316406,
      "price_to_earnings": 50.141620084729496,
      "price_to_fcf": 29.11251196450806
    },
    {
      "fiscal_year": "2020-10-31",
      "source": "sec-edgar",
      "revenue": 5603056000,
      "net_income": 1220761000,
      "operating_cash_flow": 2008487000,
      "capital_expenditure": -165692000,
      "diluted_eps": 3.28,
      "diluted_shares": 371973000,
      "free_cash_flow": 1842795000,
      "revenue_per_share": 15.063071782091711,
      "free_cash_flow_per_share": 4.95410957246897,
      "net_margin": 0.217874138684318,
      "cash_conversion": 1.5095460946081993,
      "year_end_price": 118.52999877929688,
      "price_to_earnings": 36.137194749785635,
      "price_to_fcf": 23.925590874693818
    },
    {
      "fiscal_year": "2019-02-02",
      "source": "sec-edgar",
      "revenue": 1541101000,
      "net_income": 1363011000,
      "operating_cash_flow": 2253100000,
      "capital_expenditure": -275372000,
      "diluted_eps": 0.95,
      "diluted_shares": 372506000,
      "free_cash_flow": 1977728000,
      "revenue_per_share": 4.137117254487176,
      "free_cash_flow_per_share": 5.309251394608409,
      "net_margin": 0.8844397609241704,
      "cash_conversion": 1.4509992949433277,
      "year_end_price": 100.54000091552734,
      "price_to_earnings": 105.83157991108142,
      "price_to_fcf": 18.936756511026505
    },
    {
      "fiscal_year": "2018-08-04",
      "source": "sec-edgar",
      "revenue": 1558189000,
      "net_income": 1506980000,
      "operating_cash_flow": 2442361000,
      "capital_expenditure": -254876000,
      "diluted_eps": 1.08,
      "diluted_shares": 375815000,
      "free_cash_flow": 2187485000,
      "revenue_per_share": 4.146159679629605,
      "free_cash_flow_per_share": 5.820643135585328,
      "net_margin": 0.9671355657112198,
      "cash_conversion": 1.4515687003145363,
      "year_end_price": 96.55999755859375,
      "price_to_earnings": 89.40740514684606,
      "price_to_fcf": 16.589231689580913
    }
  ],
  "historical_metrics": {
    "available_growth_windows": {
      "revenue": [
        1,
        3,
        5
      ],
      "earnings": [
        1,
        3,
        5
      ],
      "free_cash_flow": [
        1,
        3,
        5
      ]
    },
    "growth": {
      "revenue": {
        "1y": 0.16893216056548122,
        "3y": -0.028383891841526898,
        "5y": 0.14485112925375,
        "10y": null
      },
      "earnings": {
        "1y": 0.38652200580575835,
        "3y": -0.06214171851476524,
        "5y": 0.1318197742829601,
        "10y": null
      },
      "free_cash_flow": {
        "1y": 0.37045469250169605,
        "3y": 0.04252862506739885,
        "5y": 0.18349369163147533,
        "10y": null
      }
    },
    "averages": {
      "net_margin": {
        "1y": 0.20575338346110292,
        "3y": 0.2161913735122778,
        "5y": 0.21346954075782104,
        "10y": null
      },
      "cash_conversion": {
        "1y": 1.887077467801505,
        "3y": 1.6230556203197348,
        "5y": 1.5925830615235683,
        "10y": null
      },
      "price_to_earnings": {
        "1y": 51.34429931640626,
        "3y": 48.20090179594877,
        "5y": 44.46810337576515,
        "10y": null
      },
      "price_to_fcf": {
        "1y": 27.180180803603218,
        "3y": 28.68069748614413,
        "5y": 27.04554717273558,
        "10y": null
      }
    }
  },
  "calculator_contract": {
    "forward_models": {
      "revenue_growth": {
        "base": "valuation_bases.revenue.per_share",
        "margin": "user_input.net_margin",
        "terminal_multiple": "user_input.terminal_pe"
      },
      "earnings_growth": {
        "base": "valuation_bases.earnings.per_share",
        "terminal_multiple": "user_input.terminal_pe"
      },
      "fcf_growth": {
        "base": "valuation_bases.free_cash_flow.per_share",
        "terminal_multiple": "user_input.terminal_price_to_fcf"
      }
    },
    "common_user_inputs": [
      "projection_years",
      "growth_rate",
      "discount_rate"
    ],
    "forward_output": "fair_value_per_share",
    "reverse_output": "implied_compound_growth_rate"
  },
  "data_quality": {
    "warnings": []
  }
}
